{"U1TYYJbq9IdMzDUfqT4ySA==":"t%C5%82o-2000x958.jpg","YsOkYfg6Km45Jc2olTz7Aw==":"logo1-122x122.png","AyVj2tMaBoZ9kt+rWqMsVg==":"logo2-122x122.png","fEtEijajNs+pCRwWuMAiEA==":"logo1-1-122x122.png","8ltPDNsE4kw6dDCh1k/EwQ==":"logo2-1-122x122.png","ChRFPFDRn27G3yNMNIrFew==":"logo2-192x192.png","nMkww6HfPbD85ADU5bFCBA==":"mood-122x122.png","L6pdE8Nanvo0KZ6DqKYpSw==":"mood-192x192.png","pGsm6Jk1bQD5RpGy26RSCA==":"img_20191117-110712-2000x2667.jpg","qIeCxp3IqltoWFLjhuTYVw==":"icon-2000x2667.jpg","tNh/4PIWeceHIaN/t7AzCA==":"img_20191117-110241-2000x713.jpg","3XJrfcbui578WB9bo0TQ9Q==":"img_20191117-110314-2000x1169.jpg","RfThBNvzmr2lY+hwMnPr8Q==":"logo-206x108.jpg","po0K8ryOQMBMgVicoWvITw==":"img_20191117-110614-2000x958.jpg","GXEqExYptV+d5PVRjvmF7g==":"img_20191117-110512-2000x917.jpg","z7WGP2yagxbVWBVpKKZ1hw==":"img_20191117-110844-2000x2667.jpg","fySZlxUhBqCDNeo1waad1A==":"img_20191117-110844-2000x2667.jpeg","LkZn2KcUO/qcx0tVsBeZYg==":"uc-1299x1300.jpg","c3Ndr8vfR15gi6i+htz2GA==":"uc1-1170x552.png","yvpxGZxMFraJ84h5XMaQyg==":"under-construction-page-in-wp.webp","5UmzJ4LvhVHGOth+MfK5fw==":"website-under-construction-bigalbaloo-stock-900x393.jpg","+MQA6QngQEbEP8gLhpmNvQ==":"uc-1299x1300.jpeg","O64nlvi+b2R57wKdJTft4w==":"pb230011-2000x1501.jpg","KVUlv0TSVtmxS+WDf7TcZg==":"pb230027-2000x1537.jpg","UgP31b7Qjq7pxdqJyE/1WA==":"pb230028-2000x1500.jpg","IlDCn4oaBQ36c6i+nFHbvw==":"pb230039-2000x887.jpg","Y1t9WeSryueq3mp0edd1ag==":"pb230016-2000x1500.jpg","2udC7DSBZ4u8kaqnKP3tKw==":"pb230016-2000x1500.jpeg","14zCiWqwZApU2u7G3Q7ILg==":"pb230030-2000x1500.jpg","9mdzz0HPOgCZRPSK/VkklQ==":"pb230025-2000x1500.jpeg","CXIri6LGLc/hjGVaOqiuBw==":"pb230019-2000x1500.jpg","tTZ4oBJhlxnOwrXXVPId1w==":"pb230019-2000x1500.jpeg","WOOwS1QPttWS8vG4XcE2zQ==":"pb230032-2000x1500.jpg","jPOA1eHT5tkMtwKsPN2m0Q==":"pb230032-2000x1500.jpeg","FIfGrb5v7Ij/G/oWtAfVTQ==":"pb240071-2000x856.jpg"}